{
    "category": {
        "id": "ui",
        "label": "User Interface",
        "subcategories": [
            {
                "id": "font",
                "label": "Font"
            }
        ]
    },
    "settings": [
        {
            "key": "ui.fontSize",
            "type": "number",
            "default": 13,
            "description": "Controls the font size in the user interface.",
            "category": "ui",
            "subcategory": "font"
        },
        {
            "key": "ui.fontFamily",
            "type": "string",
            "default": "'Google Sans Flex', sans-serif",
            "description": "Controls the font family for the entire user interface (file explorer, sidebars, settings, etc.).",
            "category": "ui",
            "subcategory": "font"
        }
    ]
}